AUTHORS
LICENCE
MANIFEST.in
README.rst
RELEASE-NOTES
app.fil
electrum.conf.sample
electrum.desktop
icons.qrc
reddcoin-electrum
setup.py
data/README
data/noface.svg
data/cleanlook/name.cfg
data/cleanlook/style.css
data/dark/name.cfg
data/dark/style.css
data/sahara/name.cfg
data/sahara/style.css
data/wordlist/english.txt
data/wordlist/japanese.txt
data/wordlist/portuguese.txt
data/wordlist/spanish.txt
docs/android.html
docs/cold_storage
docs/console.html
gui/__init__.py
gui/android.py
gui/gtk.py
gui/stdio.py
gui/text.py
gui/qt/__init__.py
gui/qt/amountedit.py
gui/qt/console.py
gui/qt/history_widget.py
gui/qt/icons_rc.py
gui/qt/installwizard.py
gui/qt/lite_window.py
gui/qt/main_window.py
gui/qt/network_dialog.py
gui/qt/password_dialog.py
gui/qt/paytoedit.py
gui/qt/qrcodewidget.py
gui/qt/qrtextedit.py
gui/qt/qrwindow.py
gui/qt/receiving_widget.py
gui/qt/seed_dialog.py
gui/qt/transaction_dialog.py
gui/qt/util.py
gui/qt/version_getter.py
icons/.DS_Store
icons/clock1.png
icons/clock2.png
icons/clock3.png
icons/clock4.png
icons/clock5.png
icons/cold_seed.png
icons/confirmed.png
icons/dark_background.png
icons/electrum.ico
icons/electrum.png
icons/electrum_dark_icon.png
icons/electrum_light_icon.png
icons/hot_seed.png
icons/key.png
icons/lock.png
icons/network.png
icons/preferences.png
icons/qrcode.png
icons/seed.png
icons/status_connected.png
icons/status_disconnected.png
icons/status_lagging.png
icons/status_waiting.png
icons/switchgui.png
icons/trustedcoin.png
icons/unconfirmed.png
icons/unlock.png
lib/__init__.py
lib/account.py
lib/aes.py
lib/bitcoin.py
lib/blockchain.py
lib/bmp.py
lib/commands.py
lib/daemon.py
lib/i18n.py
lib/interface.py
lib/kgw.py
lib/mnemonic.py
lib/msqr.py
lib/network.py
lib/network_proxy.py
lib/old_mnemonic.py
lib/paymentrequest.py
lib/paymentrequest_pb2.py
lib/plugins.py
lib/qrscanner.py
lib/ripemd.py
lib/scrypt.py
lib/simple_config.py
lib/synchronizer.py
lib/transaction.py
lib/util.py
lib/verifier.py
lib/version.py
lib/wallet.py
lib/x509.py
reddcoin_electrum.egg-info/PKG-INFO
reddcoin_electrum.egg-info/SOURCES.txt
reddcoin_electrum.egg-info/dependency_links.txt
reddcoin_electrum.egg-info/requires.txt
reddcoin_electrum.egg-info/top_level.txt
