Metadata-Version: 1.1
Name: reddcoin-electrum
Version: 1.0.5
Summary: Reddcoin Electrum wallets for desktop
Home-page: https://wallet.reddcoin.com
Author: Larry Ren
Author-email: ren@reddcoin.com
License: GNU GPLv3
Download-URL: https://pypi.python.org/packages/source/l/reddcoin-electrum/reddcoin-electrum-1.0.5.tar.gz
Platform: All
Classifier: Environment :: Console
Classifier: Environment :: X11 Applications :: Qt
Classifier: Development Status :: 4 - Beta
Classifier: Intended Audience :: End Users/Desktop
Classifier: Intended Audience :: Developers
Classifier: License :: OSI Approved :: GNU General Public License v3 (GPLv3)
Classifier: Programming Language :: Python :: 2
Classifier: Programming Language :: Python :: 3
Classifier: Operating System :: OS Independent
Classifier: Topic :: Office/Business :: Financial
Classifier: Topic :: Software Development :: Libraries :: Python Modules
